{
  "0": "Matching Engine & Order Book",
  "1": "Order Submission & Validation",
  "2": "Order Cancellation & Active Orders",
  "3": "Settlement & Fulfillment",
  "4": "Buy/Menu/Orders Commands",
  "5": "Database Service & History",
  "6": "Market Depth GUI",
  "7": "Plugin Lifecycle & Player Events",
  "8": "Database Write Tasks",
  "9": "Admin Commands & Config",
  "10": "Documentation & Resource Files",
  "11": "Chat Input Capture",
  "12": "Configuration Loading",
  "13": "Command Dispatcher",
  "14": "Order Entry GUI",
  "15": "GUI Navigation",
  "16": "GUI Session Management",
  "17": "Market Order Command",
  "18": "Price Command",
  "19": "Sell Command",
  "20": "GUI Inventory Listeners",
  "21": "Item Creation Utilities",
  "22": "GUI Manager Core",
  "23": "SubCommand Interface",
  "24": "Database Write Queue",
  "25": "Database Write Task Base",
  "26": "Plugin Manager",
  "27": "Text Utilities",
  "29": "OpenCode Configuration",
  "30": "OpenCode Package",
  "31": "VS Code Settings",
  "32": "Graphify OpenCode Plugin",
  "33": "GUI Session Enum",
  "34": "GUI Type Enum",
  "35": "Order Side Enum",
  "36": "Order Status Enum",
  "37": "Order Type Enum"
}
